paddle_gpu_serving/__init__.py
paddle_gpu_serving/run/__init__.py
paddle_gpu_serving/server/conf/cube.conf
paddle_gpu_serving/server/conf/gflags.conf
paddle_gpu_serving/server/conf/model_toolkit.prototxt
paddle_gpu_serving/server/conf/model_toolkit.prototxt.0
paddle_gpu_serving/server/conf/model_toolkit.prototxt.1
paddle_gpu_serving/server/conf/model_toolkit.prototxt.10
paddle_gpu_serving/server/conf/model_toolkit.prototxt.11
paddle_gpu_serving/server/conf/model_toolkit.prototxt.12
paddle_gpu_serving/server/conf/model_toolkit.prototxt.13
paddle_gpu_serving/server/conf/model_toolkit.prototxt.14
paddle_gpu_serving/server/conf/model_toolkit.prototxt.15
paddle_gpu_serving/server/conf/model_toolkit.prototxt.2
paddle_gpu_serving/server/conf/model_toolkit.prototxt.3
paddle_gpu_serving/server/conf/model_toolkit.prototxt.4
paddle_gpu_serving/server/conf/model_toolkit.prototxt.5
paddle_gpu_serving/server/conf/model_toolkit.prototxt.6
paddle_gpu_serving/server/conf/model_toolkit.prototxt.7
paddle_gpu_serving/server/conf/model_toolkit.prototxt.8
paddle_gpu_serving/server/conf/model_toolkit.prototxt.9
paddle_gpu_serving/server/conf/resource.prototxt
paddle_gpu_serving/server/conf/resource.prototxt.0
paddle_gpu_serving/server/conf/resource.prototxt.1
paddle_gpu_serving/server/conf/resource.prototxt.10
paddle_gpu_serving/server/conf/resource.prototxt.11
paddle_gpu_serving/server/conf/resource.prototxt.12
paddle_gpu_serving/server/conf/resource.prototxt.13
paddle_gpu_serving/server/conf/resource.prototxt.14
paddle_gpu_serving/server/conf/resource.prototxt.15
paddle_gpu_serving/server/conf/resource.prototxt.2
paddle_gpu_serving/server/conf/resource.prototxt.3
paddle_gpu_serving/server/conf/resource.prototxt.4
paddle_gpu_serving/server/conf/resource.prototxt.5
paddle_gpu_serving/server/conf/resource.prototxt.6
paddle_gpu_serving/server/conf/resource.prototxt.7
paddle_gpu_serving/server/conf/resource.prototxt.8
paddle_gpu_serving/server/conf/resource.prototxt.9
paddle_gpu_serving-0.8.3.dist-info/METADATA
paddle_gpu_serving-0.8.3.dist-info/WHEEL
paddle_gpu_serving-0.8.3.dist-info/top_level.txt
paddle_gpu_serving-0.8.3.dist-info/RECORD
