Metadata-Version: 2.1
Name: paddle-gpu-serving
Version: 0.8.3
Summary: package for paddle serving with bert
Home-page: https://github.com/PaddlePaddle/Serving
Author: MRXLT
Author-email: xlt2024@gmail.com
License: UNKNOWN
Platform: UNKNOWN
Classifier: Programming Language :: Python :: 3
Classifier: License :: OSI Approved :: MIT License
Classifier: Operating System :: OS Independent
Requires-Python: >=3.5
